flood_napari/__init__.py
flood_napari/_dock_widget.py
flood_napari/_tests/__init__.py
flood_napari/_tests/test_dock_widget.py
flood_napari-0.0.2.dist-info/LICENSE
flood_napari-0.0.2.dist-info/METADATA
flood_napari-0.0.2.dist-info/WHEEL
flood_napari-0.0.2.dist-info/entry_points.txt
flood_napari-0.0.2.dist-info/top_level.txt
flood_napari-0.0.2.dist-info/RECORD
