Metadata-Version: 2.1
Name: flood-napari
Version: 0.0.2
Summary: A simple plugin to flood 8-bit 2D images by means of a big blue label
Home-page: https://github.com/zoccoler/flood-napari
Author: Marcelo Leomil Zoccoler
Author-email: marcelo.zoccoler@tu-dresden.de
License: BSD-3-Clause
Project-URL: Bug Tracker, https://github.com/zoccoler/flood-napari/issues
Project-URL: Documentation, https://github.com/zoccoler/flood-napari#README.md
Project-URL: Source Code, https://github.com/zoccoler/flood-napari
Project-URL: User Support, https://github.com/zoccoler/flood-napari/issues
Platform: UNKNOWN
Classifier: Development Status :: 2 - Pre-Alpha
Classifier: Intended Audience :: Developers
Classifier: Topic :: Software Development :: Testing
Classifier: Programming Language :: Python
Classifier: Programming Language :: Python :: 3
Classifier: Programming Language :: Python :: 3.7
Classifier: Programming Language :: Python :: 3.8
Classifier: Programming Language :: Python :: 3.9
Classifier: Operating System :: OS Independent
Classifier: License :: OSI Approved :: BSD License
Requires-Python: >=3.7
License-File: LICENSE
Requires-Dist: napari-plugin-engine (>=0.1.4)
Requires-Dist: numpy
